koslang/__init__.py
koslang/data.csv
koslang/koslang.py
koslang-0.1.0.dist-info/METADATA
koslang-0.1.0.dist-info/WHEEL
koslang-0.1.0.dist-info/top_level.txt
koslang-0.1.0.dist-info/RECORD
