Metadata-Version: 2.1
Name: koslang
Version: 0.1.0
Summary: This Package can detect slang in Korean sentence.
Author: ChoiJaeHoon
Author-email: diadiahun0902@gmail.com
License: MIT
Requires-Python: >=3.8
Requires-Dist: eunjeon
Requires-Dist: pandas
